nfgan/Debug.py
nfgan/__init__.py
nfgan-0.0.3.dist-info/LICENSE.text
nfgan-0.0.3.dist-info/METADATA
nfgan-0.0.3.dist-info/WHEEL
nfgan-0.0.3.dist-info/top_level.txt
nfgan-0.0.3.dist-info/RECORD
